jupyter_brat_proxy/__init__.py
jupyter_brat_proxy/brat_favicon.svg
jupyter_brat_proxy-0.0.2.dist-info/METADATA
jupyter_brat_proxy-0.0.2.dist-info/WHEEL
jupyter_brat_proxy-0.0.2.dist-info/entry_points.txt
jupyter_brat_proxy-0.0.2.dist-info/licenses/LICENSE.md
jupyter_brat_proxy-0.0.2.dist-info/RECORD
