Metadata-Version: 2.4
Name: jupyter-brat-proxy
Version: 0.0.2
Summary: BRAT jupyter server proxy
Project-URL: Homepage, https://github.com/huntdatacenter/jupyter-brat-proxy
Author-email: Matus Kosut <matus.kosut@ntnu.no>, Melissa Yan <melissa.yan@ntnu.no>, HUNT Cloud <cloud@hunt.ntnu.no>
License: MIT License
License-File: LICENSE.md
Keywords: Jupyter Proxy,Jupyter Server Proxy,JupyterLab
Classifier: Framework :: Jupyter
Classifier: Framework :: Jupyter :: JupyterLab
Classifier: Intended Audience :: Developers
Classifier: License :: OSI Approved :: MIT License
Classifier: Natural Language :: English
Classifier: Programming Language :: Python :: 3
Classifier: Programming Language :: Python :: 3.8
Classifier: Programming Language :: Python :: 3.9
Classifier: Programming Language :: Python :: 3.10
Classifier: Programming Language :: Python :: 3.11
Classifier: Programming Language :: Python :: 3.12
Classifier: Programming Language :: Python :: 3.13
Requires-Python: >=3.8
Requires-Dist: bratserver==0.0.1
Requires-Dist: jupyter-server-proxy
Provides-Extra: dev
Requires-Dist: black; extra == 'dev'
Requires-Dist: pytest; extra == 'dev'
Requires-Dist: pytest-cov; extra == 'dev'
Requires-Dist: ruamel-yaml; extra == 'dev'
